wildfire_drone/Drone.py
wildfire_drone/Strategy.py
wildfire_drone/__init__.py
wildfire_drone/benchmark.py
wildfire_drone/dataset.py
wildfire_drone/displays.py
wildfire_drone/my_julia_caller.py
wildfire_drone/new_clustering.py
wildfire_drone/parallelize.py
wildfire_drone/wrappers.py
wildfire_drone-0.1.0.dist-info/licenses/LICENSE
wildfire_drone-0.1.0.dist-info/METADATA
wildfire_drone-0.1.0.dist-info/WHEEL
wildfire_drone-0.1.0.dist-info/entry_points.txt
wildfire_drone-0.1.0.dist-info/top_level.txt
wildfire_drone-0.1.0.dist-info/RECORD
