Metadata-Version: 2.4
Name: wildfire_drone
Version: 0.1.0
Summary: A wildfire detection drone routing library
Home-page: https://github.com/RomainPuech/wildfire_drone_routing
Author: Joseph Ye
Classifier: Programming Language :: Python :: 3
Classifier: Operating System :: OS Independent
Requires-Python: >=3.8
License-File: LICENSE
Requires-Dist: numpy
Requires-Dist: matplotlib
Requires-Dist: opencv-python
Requires-Dist: Pillow
Requires-Dist: torch
Requires-Dist: tqdm
Requires-Dist: scikit-learn
Requires-Dist: scipy
Requires-Dist: juliacall
Dynamic: author
Dynamic: classifier
Dynamic: description
Dynamic: description-content-type
Dynamic: home-page
Dynamic: license-file
Dynamic: requires-dist
Dynamic: requires-python
Dynamic: summary
